mlservicewrapper/host/http/__init__.py
mlservicewrapper/host/http/__main__.py
mlservicewrapper/host/http/server.py
mlservicewrapper_host_http-0.5.1.dist-info/LICENSE
mlservicewrapper_host_http-0.5.1.dist-info/METADATA
mlservicewrapper_host_http-0.5.1.dist-info/WHEEL
mlservicewrapper_host_http-0.5.1.dist-info/top_level.txt
mlservicewrapper_host_http-0.5.1.dist-info/RECORD
