Metadata-Version: 2.1
Name: mlservicewrapper-host-http
Version: 0.5.1
Summary: Host an mlservicewrapper service using HTTP
Home-page: https://github.com/ml-service-wrapper/ml-service-wrapper-host-http
Author: Matthew Haugen
Author-email: mhaugen@haugenapplications.com
License: UNKNOWN
Platform: UNKNOWN
Requires-Python: >=3.6
Requires-Dist: mlservicewrapper-core (~=0.7)
Requires-Dist: starlette (~=0.13)
Requires-Dist: uvicorn
Requires-Dist: gunicorn
Requires-Dist: httptools
Requires-Dist: uvloop
